{
"type": "FeatureCollection",
"name": "14_booking_windows",
"crs": { "type": "name", "properties": { "name": "urn:ogc:def:crs:OGC:1.3:CRS84" } },
"features": [
{ "type": "Feature", "properties": { "ventana_fecha": "2025-11-01_2025-11-04", "check_in": "2025-11-01", "check_out": "2025-11-04", "total_properties": 1229, "avg_price_per_window": 10.216436126932491, "median_price": 3.0, "min_price": 1.0, "max_price": 993.0, "avg_stay_nights": 3.0, "properties_with_rating": 816, "avg_rating": 3.176436126932467, "center_lon": -89.633077754056814, "center_lat": 21.00221119676149 }, "geometry": { "type": "Point", "coordinates": [ -89.633077754056814, 21.00221119676149 ] } },
{ "type": "Feature", "properties": { "ventana_fecha": "2025-11-08_2025-11-11", "check_in": "2025-11-08", "check_out": "2025-11-11", "total_properties": 1316, "avg_price_per_window": 11.358662613981762, "median_price": 3.0, "min_price": 1.0, "max_price": 993.0, "avg_stay_nights": 3.0, "properties_with_rating": 888, "avg_rating": 3.2247872340425521, "center_lon": -89.636242901647435, "center_lat": 21.001448635812292 }, "geometry": { "type": "Point", "coordinates": [ -89.636242901647435, 21.001448635812292 ] } },
{ "type": "Feature", "properties": { "ventana_fecha": "2025-11-15_2025-11-18", "check_in": "2025-11-15", "check_out": "2025-11-18", "total_properties": 1419, "avg_price_per_window": 12.015503875968918, "median_price": 3.0, "min_price": 1.0, "max_price": 998.0, "avg_stay_nights": 3.0, "properties_with_rating": 998, "avg_rating": 3.359598308668077, "center_lon": -89.636596964129168, "center_lat": 21.00270403132301 }, "geometry": { "type": "Point", "coordinates": [ -89.636596964129168, 21.00270403132301 ] } },
{ "type": "Feature", "properties": { "ventana_fecha": "2025-11-22_2025-11-25", "check_in": "2025-11-22", "check_out": "2025-11-25", "total_properties": 1357, "avg_price_per_window": 10.168017686072186, "median_price": 3.0, "min_price": 1.0, "max_price": 998.0, "avg_stay_nights": 3.0, "properties_with_rating": 940, "avg_rating": 3.3069123065585844, "center_lon": -89.637824881994945, "center_lat": 21.001232948362045 }, "geometry": { "type": "Point", "coordinates": [ -89.637824881994945, 21.001232948362045 ] } }
]
}
